mcp_server/__init__.py
mcp_server/server.py
mcp_server/utils.py
mseep_tidal_mcp-0.1.1.dist-info/licenses/LICENSE
tidal_api/__init__.py
tidal_api/app.py
tidal_api/browser_session.py
tidal_api/utils.py
mseep_tidal_mcp-0.1.1.dist-info/METADATA
mseep_tidal_mcp-0.1.1.dist-info/WHEEL
mseep_tidal_mcp-0.1.1.dist-info/top_level.txt
mseep_tidal_mcp-0.1.1.dist-info/RECORD
